MANIFEST.in
README.md
setup.py
rungsted/MurmurHash3.cpp
rungsted/MurmurHash3.h
rungsted/__init__.py
rungsted/corruption.cpp
rungsted/corruption.pyx
rungsted/decoding.cpp
rungsted/decoding.pyx
rungsted/feat_map.cpp
rungsted/feat_map.pyx
rungsted/input.cpp
rungsted/input.pyx
rungsted/labeler.py
rungsted/local_rd_parser.py
rungsted/struct_perceptron.cpp
rungsted/struct_perceptron.pyx
rungsted/timer.py
rungsted/weights.cpp
rungsted/weights.pyx
rungsted.egg-info/PKG-INFO
rungsted.egg-info/SOURCES.txt
rungsted.egg-info/dependency_links.txt
rungsted.egg-info/entry_points.txt
rungsted.egg-info/requires.txt
rungsted.egg-info/top_level.txt