Metadata-Version: 1.1
Name: rungsted
Version: 1.2.4
Summary: Rungsted. An efficient HMM-based structured prediction model for sequential labeling tasks, with extras. 
Home-page: https://github.com/coastalcph/rungsted
Author: Anders Johannsen
Author-email: ajohannsen@hum.ku.dk
License: MIT
Keywords: hmm perceptron structured_model
Platform: UNKNOWN
Classifier: Development Status :: 4 - Beta
Classifier: Programming Language :: Python :: 3.4
Classifier: License :: OSI Approved :: MIT License
Classifier: Topic :: Scientific/Engineering
Classifier: Topic :: Scientific/Engineering :: Artificial Intelligence
